LICENSE
MANIFEST.in
README.rst
setup.cfg
setup.py
kglib/__init__.py
kglib.egg-info/PKG-INFO
kglib.egg-info/SOURCES.txt
kglib.egg-info/dependency_links.txt
kglib.egg-info/requires.txt
kglib.egg-info/top_level.txt
kglib/cross_correlation/Analyze_CCF.py
kglib/cross_correlation/CCF_Systematics.py
kglib/cross_correlation/CCF_Widget.py
kglib/cross_correlation/Correct_CCF_Temperatures.py
kglib/cross_correlation/Correlate.py
kglib/cross_correlation/GenericSearch.py
kglib/cross_correlation/Normalized_Xcorr.py
kglib/cross_correlation/Sensitivity.py
kglib/cross_correlation/__init__.py
kglib/fitters/__init__.py
kglib/fitters/bayesian.py
kglib/fitters/histogram.py
kglib/fitters/linear.py
kglib/isochrone_helpers/Feiden.py
kglib/isochrone_helpers/__init__.py
kglib/spectral_type/Mamajek_Table.py
kglib/spectral_type/SpectralTypeRelations.py
kglib/spectral_type/__init__.py
kglib/spectral_type/data/Mamajek_Table.txt
kglib/spectral_type/data/Pecaut2013.tsv
kglib/stellar_data/__init__.py
kglib/stellar_data/creators.py
kglib/stellar_data/readers.py
kglib/stellar_data/data/Stars.sqlite
kglib/stellar_models/Broaden.py
kglib/stellar_models/RotBroad_Fast.c
kglib/stellar_models/StellarModel.py
kglib/stellar_models/__init__.py
kglib/utils/DataStructures.py
kglib/utils/FittingUtilities.c
kglib/utils/HDF5_Helpers.py
kglib/utils/HelperFunctions.py
kglib/utils/IMF_utils.py
kglib/utils/PlotBlackbodies.py
kglib/utils/StarData.py
kglib/utils/Units.py
kglib/utils/__init__.py
kglib/utils/plottools.py
kglib/utils/readmultispec.py
kglib/utils/synthetic_photometry.py