Metadata-Version: 1.1
Name: kglib
Version: 0.2.0
Summary: A series of packages for my analysis
Home-page: https://github.com/kgullikson88/gullikson-scripts
Author: Kevin Gullikson
Author-email: kevin.gullikson@gmail.com
License: The MIT License: http://www.opensource.org/licenses/mit-license.php
Platform: UNKNOWN
Classifier: Development Status :: 2 - Pre-Alpha
Classifier: Intended Audience :: Developers
Classifier: Operating System :: OS Independent
Classifier: License :: OSI Approved :: MIT License
Classifier: Programming Language :: Python :: 2.7
